calc_pe/__init__.py
calc_pe/utils.py
calc_pe-1.0.1.data/scripts/calc_pe
calc_pe-1.0.1.dist-info/METADATA
calc_pe-1.0.1.dist-info/WHEEL
calc_pe-1.0.1.dist-info/top_level.txt
calc_pe-1.0.1.dist-info/RECORD
