Metadata-Version: 2.1
Name: calc-pe
Version: 1.0.1
Summary: Calculator for the CO2 parasitic energy from CO2 and N2 isotherms
Home-page: https://github.com/danieleongari/calc_pe
Author: Daniele Ongari
Author-email: daniele.ongari@epfl.ch
License: MIT
Platform: UNKNOWN
Classifier: Programming Language :: Python
Requires-Dist: numpy
Requires-Dist: pandas (>=0.24.0)
Requires-Dist: pyiast
